financial_services_register_api-1.3.0.dist-info/METADATA
financial_services_register_api-1.3.0.dist-info/WHEEL
financial_services_register_api-1.3.0.dist-info/entry_points.txt
financial_services_register_api-1.3.0.dist-info/licenses/LICENSE
financial_services_register_api/__version__.py
financial_services_register_api/api.py
financial_services_register_api/constants.py
financial_services_register_api/exceptions.py
financial_services_register_api-1.3.0.dist-info/RECORD
