Metadata-Version: 2.1
Name: financial-services-register-api
Version: 1.3.0
Summary: Python client library for the UK Financial Services Register RESTful API
Keywords: financial conduct authority,financial data,financial regulation,financial services register,financial services,prudential regulation authority,regulated markets,restful api,uk,united kingdom
Author-Email: "S. R. Murthy" <s.murthy@tutanota.com>
Maintainer-Email: "S. R. Murthy" <s.murthy@tutanota.com>
License:                     GNU GENERAL PUBLIC LICENSE
Classifier: Environment :: Console
Classifier: Programming Language :: Python :: 3
Classifier: Programming Language :: Python :: 3.11
Classifier: Programming Language :: Python :: 3.12
Classifier: Programming Language :: Python :: 3.13
Classifier: Development Status :: 5 - Production/Stable
Classifier: Operating System :: POSIX :: Linux
Classifier: Operating System :: MacOS
Classifier: Operating System :: Microsoft :: Windows
Project-URL: Homepage, https://financial-services-register-api.readthedocs.io/en/latest/
Project-URL: Documentation, https://financial-services-register-api.readthedocs.io/en/latest/
Project-URL: Repository, https://github.com/sr-murthy/financial-services-register-api
Requires-Python: >=3.11
Requires-Dist: requests
Provides-Extra: user
Requires-Dist: jupyter; extra == "user"
